mccabe.py
mccabe-0.6.0.dist-info/DESCRIPTION.rst
mccabe-0.6.0.dist-info/METADATA
mccabe-0.6.0.dist-info/RECORD
mccabe-0.6.0.dist-info/WHEEL
mccabe-0.6.0.dist-info/entry_points.txt
mccabe-0.6.0.dist-info/metadata.json
mccabe-0.6.0.dist-info/top_level.txt
